lilliepy_head/__init__.py
lilliepy_head/main.py
lilliepy_head-1.0.dist-info/METADATA
lilliepy_head-1.0.dist-info/WHEEL
lilliepy_head-1.0.dist-info/top_level.txt
lilliepy_head-1.0.dist-info/RECORD
